uGauss/__init__.py
uGauss/main.py
gaussian_elimination_libraries-1.1.dist-info/METADATA
gaussian_elimination_libraries-1.1.dist-info/WHEEL
gaussian_elimination_libraries-1.1.dist-info/top_level.txt
gaussian_elimination_libraries-1.1.dist-info/RECORD
