Metadata-Version: 2.4
Name: Gaussian_Elimination_Libraries
Version: 1.1
Author: YusufA442
Author-email: yusuf365820@gmail.com
License: Creative Commons Attribution-Noncommercial-Share Alike license
Requires-Dist: numpy>=2.2.5
Dynamic: author
Dynamic: author-email
Dynamic: description
Dynamic: license
Dynamic: requires-dist
